kpf/__init__.py
kpf/__main__.py
kpf/cli.py
kpf/config.py
kpf/connectivity.py
kpf/display.py
kpf/forwarder.py
kpf/kubernetes.py
kpf/main.py
kpf/usage_logger.py
kpf/validators.py
kpf/watcher.py
kpf-0.6.0.dist-info/METADATA
kpf-0.6.0.dist-info/WHEEL
kpf-0.6.0.dist-info/entry_points.txt
kpf-0.6.0.dist-info/licenses/LICENSE
kpf-0.6.0.dist-info/RECORD
