Metadata-Version: 2.4
Name: kpf
Version: 0.6.0
Summary: A terminal utility with a better UX for kubectl port-forward
Project-URL: Homepage, https://github.com/jessegoodier/kpf
Project-URL: Repository, https://github.com/jessegoodier/kpf
Project-URL: Issues, https://github.com/jessegoodier/kpf/issues
Author: Jesse Goodier
License: MIT License
License-File: LICENSE
Keywords: cli,devops,k8s,kubectl,kubernetes,port-forward
Classifier: Development Status :: 4 - Beta
Classifier: Environment :: Console
Classifier: Intended Audience :: System Administrators
Classifier: License :: OSI Approved :: MIT License
Classifier: Operating System :: OS Independent
Classifier: Programming Language :: Python :: 3
Classifier: Programming Language :: Python :: 3.14
Classifier: Topic :: System :: Systems Administration
Classifier: Topic :: Utilities
Requires-Python: >=3.14
Requires-Dist: prompt-toolkit>=3.0.51
Requires-Dist: readchar>=4.2.1
Requires-Dist: requests>=2.28
Requires-Dist: rich>=14
Provides-Extra: dev
Requires-Dist: bump-my-version; extra == 'dev'
Requires-Dist: coverage; extra == 'dev'
Requires-Dist: hatch; extra == 'dev'
Requires-Dist: isort; extra == 'dev'
Requires-Dist: pytest; extra == 'dev'
Requires-Dist: pytest-cov; extra == 'dev'
Requires-Dist: pytest-timeout; extra == 'dev'
Requires-Dist: ruff; extra == 'dev'
